<?xml version="1.0" encoding="UTF-8"?>
<root OneMapHome="C:\20120915">
	<Layout>
		<db>
			<db_ip name="数据库服务器IP:">127.0.0.2</db_ip>
			<db_port name="数据库服务器PORT:">1521</db_port>
			<db_sid name="数据库服务器实例名:">orcl</db_sid>
			<manager_user name="GeoShareManager数据库用户名:">geoshare_platform</manager_user>
			<manager_pwd name="GeoShareManager数据库密码:" encrypt="true">Gzt3XR0PAto=</manager_pwd>
			<portal_user name="GeoSharePortal数据库用户名:">geoshare_portal</portal_user>
			<portal_pwd name="GeoSharePortal数据库密码:" encrypt="true">Gzt3XR0PAto=</portal_pwd>
			<geocoding_user name="GeoCoding数据库用户名:">geo_coding</geocoding_user>
			<geocoding_pwd name="GeoCoding数据库密码:" encrypt="true">Gzt3XR0PAto=</geocoding_pwd>
			<geoportal_user name="GeoPortal数据库用户名:">geo_portal</geoportal_user>
			<geoportal_pwd name="GeoPortal数据库密码:" encrypt="true">Gzt3XR0PAto=</geoportal_pwd>
			<db_h2 name="内存数据库IP:">127.0.0.2</db_h2>
			<sub_user name="分平台数据库用户名:">GEOSHARE_SUB_PLATFORM</sub_user>
		</db>
		<web>
			<web_ip name="门户IP:">127.0.0.2</web_ip>
			<web_port name="门户PORT:">8080</web_port>
        <web_user name="门户默认用户名:">super</web_user>
        <web_pwd name="门户默认用户名密码:">admin</web_pwd>
        <flex_ip name="Flex发布服务器IP:">127.0.0.2</flex_ip>
        <flex_port name="Flex发布服务器PORT:">8080</flex_port>
        <sl_ip name="Silverlight发布服务器IP:">127.0.0.2</sl_ip>
        <sl_port name="Silverlight发布服务器PORT:">80</sl_port>
        <ria_ip name="快速搭建服务器IP:">127.0.0.2</ria_ip>
        <ria_port name="快速发布服务器PORT:">8080</ria_port>
        <iis_root name="silverlight文件生成路径:">c:\inetpub\wwwroot\</iis_root>
        <web_csw name="是否启用CSW服务:" selects="0,禁用;1,开启">1</web_csw>
    </web>
    <gis>
        <gis_ip name="GIS服务器IP:">127.0.0.2</gis_ip>
        <gis_port name="GIS服务器PORT:">8080</gis_port>
        <gis_ags_ip name="ArcGISServer服务器IP:">127.0.0.2</gis_ags_ip>
        <gis_ags_user name="ArcGISServer服务器用户名:">arcgismanager</gis_ags_user>
        <gis_ags_pwd name="ArcGISServer服务器密码:" encrypt="true">/2IWry6fWdsq9l5S69ER8Q==</gis_ags_pwd>
        <gis_sharekey name="sharekey:" encrypt="true">9STRE5GPzs2UpCvzrlfktw==</gis_sharekey>
			<ags_log_path name="ArcGISServer日志本地存放目录:">C:\ArcGIS\Server10.0\server\user\log</ags_log_path>
			<!--gis_base_map name="底图服务地址:">http://127.0.0.1:8099/arcgis/rest/services/world/MapServer</gis_base_map>
			<gis_geo_map name="几何服务地址:">http://127.0.0.1:8099/arcgis/rest/services/Geometry/GeometryServer</gis_geo_map-->
			<gis_basemap_type name="底图服务类型:">dynamic</gis_basemap_type>
			<gis_services_port name="RemoteServices系统的HTTPSPORT:">8443</gis_services_port>
			<wmts_ip name="WMTS系统的IP:">127.0.0.2</wmts_ip>
			<wmts_port name="WMTS系统的PORT:">8080</wmts_port>	
			<!--web_base_map name="基础底图路径:">http://127.0.0.1:8080/RemoteRest/services/usa/MapServer</web_base_map-->		
			<sysrest_ip name="SysRest服务IP:">127.0.0.2</sysrest_ip>
			<sysrest_port name="SysRest服务PORT">8081</sysrest_port>
		</gis>
		<main>
			<main_ip name="运维服务器IP:">127.0.0.2</main_ip>
			<main_port name="运维服务器PORT:">8080</main_port>
			<main_upload_level name="运维文件上传目录深度:">3</main_upload_level>
			<main_upload_num name="运维文件上传最大值:">1</main_upload_num>
			<geoconding_ip name="GeoCoding系统的IP:">127.0.0.2</geoconding_ip>
			<geoconding_port name="GeoCoding系统的PORT:">8080</geoconding_port>
			<geoportal_ip name="GeoPortal系统的IP:">127.0.0.2</geoportal_ip>
			<geoportal_port name="GeoPortal系统的PORT:">8080</geoportal_port>
			<sub_upload_num name="分平台文件上传最大值">10</sub_upload_num>
            <sub_syn_code name="分平台同步代码" selects="0,主分平台之间进行同步; 1,主主平台之间进行同步;">0</sub_syn_code>
			<file_ip name="FileServices系统的IP:">127.0.0.2</file_ip>
			<file_port name="FileServices系统的PORT号:">8080</file_port>			
			<tile_ip name="TileServices系统的IP:">127.0.0.2</tile_ip>
			<tile_port name="TileServices系统的PORT:">8080</tile_port>
			<aggregator_ip name="Aggregator系统的IP:">127.0.0.2</aggregator_ip>
			<aggregator_port name="Aggregator系统的PORT:">8080</aggregator_port>			
		</main>
		<token>
			<token_ip name="Token服务器ip:">127.0.0.2</token_ip>
			<token_port name="Token服务器PORT:">8080</token_port>
		</token>
		<msg>
			<msg_ip name="JMS服务器ip:">127.0.0.2</msg_ip>
			<msg_port name="JMS服务器PORT:">61616</msg_port>
		</msg>
		<agent>
			<agent_ip name="监控代理服务器IP:">127.0.0.2</agent_ip>
			<agent_port name="监控代理服务器PORT:">8080</agent_port>
		</agent>
	</Layout>
	<FileMapping>
		<tomcat path="Tomcat6.0.29\webapps">
			<arcgis_js_api>
				<gis />
			</arcgis_js_api>
			<BufferAnalyst>
				<db>
					<file path="BufferAnalyst/WEB-INF/config/proxool.xml">
						<key template="jdbc:h2:tcp://[db_h2]/mem:geosharemdb;MODE=Oracle;DB_CLOSE_DELAY=-1;DB_CLOSE_ON_EXIT=false">/something-else-entirely/proxool[1]/driver-url</key>
						<key template="jdbc:oracle:thin:@[db_ip]:[db_port]:[db_sid]">/something-else-entirely/proxool[2]/driver-url</key>
						<key template="[manager_user]" attribute="value">/something-else-entirely/proxool[2]/driver-properties/property[@name='user']</key>
						<key template="[manager_pwd]" attribute="value">/something-else-entirely/proxool[2]/driver-properties/property[@name='password']</key>
					</file>			
				</db>
				<gis>
					<file path="BufferAnalyst/WEB-INF/config/logback.xml">
						<key template="[TomcatAppPath]/BufferAnalyst/WEB-INF/logs" attribute="value">/configuration/property</key>
					</file>
				</gis>
			</BufferAnalyst>
			<GeoCoding>
				<db>
					<file path="GeoCoding/WEB-INF/classes/data/db.properties">
						<key template="jdbc:oracle:thin:@[db_ip]:[db_port]:[db_sid]">url</key>
						<key template="[geocoding_user]">username</key>
						<key template="[geocoding_pwd]">password</key>	
					</file>	
					<file path="GeoCoding/WEB-INF/web.xml">
						<key template="[OneMapHome]\arcgis\license">/default:web-app/default:servlet[1]/default:init-param/default:param-value</key></file>				
				</db>
				<main>
					<file path="GeoCoding/WEB-INF/conf/wfs/wfs_configuration.xml">
						<key template="http://[geoconding_ip]:[geoconding_port]/GeoCoding/WFSGServer" nsattribute="href">/wfs:WFS_Capabilities/deegree:deegreeParams/deegree:DefaultOnlineResource</key>
					</file>
				</main>
			</GeoCoding>
			<GeoPortal>
				<db>
					<file path="GeoPortal/WEB-INF/proxool.xml">
						<key template="jdbc:oracle:thin:@[db_ip]:[db_port]:[db_sid]">/something-else-entirely/proxool/driver-url</key>
						<key template="[geoportal_user]" attribute="value">/something-else-entirely/proxool/driver-properties/property[@name='user']</key>
						<key template="[geoportal_pwd]" attribute="value">/something-else-entirely/proxool/driver-properties/property[@name='password']</key>
					</file>				
					<file path="GeoPortal/WEB-INF/web.xml">
						<key template="[OneMapHome]\arcgis\license">/default:web-app/default:servlet[1]/default:init-param/default:param-value</key></file>				
				</db>
				<gis>
					<file path="GeoPortal/WEB-INF/classes/gpt/config/gpt.xml">
						<key template="http://[gis_ags_ip]:8099/arcgis/rest/services/world/MapServer" attribute="mapServiceUrl">/gptConfig/interactiveMap</key>
						<key template="[gis_basemap_type]" attribute="mapServiceType">/gptConfig/interactiveMap</key>
						<key template="http://[gis_ags_ip]:8099/arcgis/rest/services/Geometry/GeometryServer" attribute="geometryServiceUrl">/gptConfig/interactiveMap</key>						
						<key template="http://[sysrest_ip]:[sysrest_port]/SysRestServices/rest/services/queryServiceByConditions" attribute="url">/gptConfig/onemap</key>
					</file>
				</gis>
			</GeoPortal>
			<GeoShareManager>
				<db>
					<file path="GeoShareManager/WEB-INF/classes/conf/hibernate.cfg.xml">
						<key template="jdbc:oracle:thin:@[db_ip]:[db_port]:[db_sid]">/hibernate-configuration/session-factory/property[@name='connection.url']</key>		
						<key template="[manager_user]">/hibernate-configuration/session-factory/property[@name='connection.username']</key>						
						<key template="[manager_pwd]">/hibernate-configuration/session-factory/property[@name='connection.password']</key></file>
					<file path="GeoShareManager/WEB-INF/classes/conf/system.properties">
						<key template="[sub_user]">branch_platform_schema</key>
					</file>
					<file path="GeoShareManager/WEB-INF/web.xml">
						<key template="[OneMapHome]\arcgis\license">/default:web-app/default:servlet[13]/default:init-param/default:param-value</key>
					</file>				
				</db>
				<gis>
					<file path="GeoShareManager/WEB-INF/classes/token_config.properties">
						<key template="[gis_sharekey]" encrypt="true">sharedkey</key></file>
					<file path="GeoShareManager/WEB-INF/conf/logclient-config.xml">
						<key template="[OneMapHome]/temp/download">/log-client/download-servers/download-path</key>
						<key template="[OneMapHome]/temp/unzip">/log-client/unzip/unzip-path</key></file>
					<file path="GeoShareManager/WEB-INF/classes/conf/system.properties">
						<key template="http://[gis_ip]:[gis_port]/arcgis/rest/services/regioncontrol/FeatureServer/0">featureservice</key>
					</file>
				</gis>
				<msg>
					<file path="GeoShareManager/WEB-INF/classes/activemqconfig.properties">
						<key template="failover:tcp://[msg_ip]:[msg_port]">brokerURL</key></file>
					<file path="GeoShareManager/WEB-INF/classes/config.properties">
						<key template="[msg_ip]">msg_ip</key>
						<key template="[msg_port]">msg_port</key></file>			
				</msg>
				<main>
					<file path="GeoShareManager/WEB-INF/classes/LocalServiceFileConfig.properties">
						<key template="[OneMapHome]\temp\ServiceUploadTemp">temppath</key>
						<key template="[OneMapHome]\temp\ServiceUploaded">path</key>
						<key template="[main_upload_level]">level</key>
						<key template="[main_upload_num]">maxfilesize</key></file>	
					<file path="GeoShareManager/WEB-INF/classes/config.properties">
						<key template="[main_ip]">client_server_ip</key></file>		
					<file path="GeoShareManager/WEB-INF/classes/conf/system.properties">
						<key template="[TomcatAppPath]\GeoShareManager\download\commonfile">physical_path_commonfile</key>
						<key template="[TomcatAppPath]\GeoShareManager\download\tilemapfile">physical_path_tilemapfile</key>
						<key template="[TomcatAppPath]\GeoShareManager\download\bundlemapfile">physical_path_bundlemapfile</key>
						<key template="http://[main_ip]:[main_port]/GeoShareManager/download/commonfile">net_path_commonfile</key>
						<key template="http://[main_ip]:[main_port]/GeoShareManager/download/tilemapfile">net_path_tilemapfile</key>
						<key template="http://[main_ip]:[main_port]/GeoShareManager/download/bundlemapfile">net_path_bundlemapfile</key>
						<key template="http://[main_ip]:[main_port]/GeoShareManager/rest">rest_base_url</key>
						<key template="[OneMapHome]/temp/branchplatform/upload/">branch_platform_uploadpath</key>
						<key template="[OneMapHome]/temp/branchplatform/tmp/">branch_platform_uploadtmppath</key>
						<key template="[sub_upload_num]">branch_platform_maxfilesize</key>
						<key template="[sub_syn_code]">platform_syncmode</key></file>
				</main>
				<token>
					<file path="GeoShareManager/WEB-INF/classes/token_config.properties">
						<key template="http://[token_ip]:[token_port]/RemoteTokenServer">token_url</key></file>				
				</token>
			</GeoShareManager>
			<LogServer>
				<gis>
					<file path="LogServer/WEB-INF/config/log4j.properties">
						<key template="[OneMapHome]/temp/ws-server">log4j.log.dir</key></file>
					<file path="LogServer/WEB-INF/config/logserver-config.xml">
						<key template="[OneMapHome]\temp\ws-server\srvmon\json">/LogServer/Resources/Resource[1]/resPath</key>
						<key template="[OneMapHome]\temp\ws-server\ziplogs\srvmon">/LogServer/Resources/Resource[1]/resZipPath</key>
						<key template="[OneMapHome]\temp\ws-server\srvmon_out\json">/LogServer/Resources/Resource[2]/resPath</key>
						<key template="[OneMapHome]\temp\ws-server\ziplogs\srvmon_out">/LogServer/Resources/Resource[2]/resZipPath</key>
						<key template="[ags_log_path]">/LogServer/Resources/Resource[3]/resPath</key>
						<key template="[OneMapHome]\temp\ws-server\ziplogs\agsrv">/LogServer/Resources/Resource[3]/resZipPath</key>		
						<key template="[OneMapHome]\temp\ws-server\srvmon_soap\json">/LogServer/Resources/Resource[4]/resPath</key>
						<key template="[OneMapHome]\temp\ws-server\ziplogs\srvmon_soap">/LogServer/Resources/Resource[4]/resZipPath</key>
						<key template="[OneMapHome]\temp\ws-server\ServiceAggregatorServer\json">/LogServer/Resources/Resource[5]/resPath</key>
						<key template="[OneMapHome]\temp\ws-server\ziplogs\ServiceAggregatorServer">/LogServer/Resources/Resource[5]/resZipPath</key>
						<key template="[OneMapHome]\temp\ws-server\TileServices\json">/LogServer/Resources/Resource[6]/resPath</key>
						<key template="[OneMapHome]\temp\ws-server\ziplogs\TileServices">/LogServer/Resources/Resource[6]/resZipPath</key>
						<key template="[OneMapHome]\temp\ws-server\FileServices\json">/LogServer/Resources/Resource[7]/resPath</key>
						<key template="[OneMapHome]\temp\ws-server\ziplogs\FileServices">/LogServer/Resources/Resource[7]/resZipPath</key>
						<key template="[OneMapHome]\temp\ws-server\branchplatform_data">/LogServer/Resources/Resource[8]/resPath</key>
						<key template="[OneMapHome]\temp\ws-server\ziplogs\branchplatform_data">/LogServer/Resources/Resource[8]/resZipPath</key>						
					</file>
				</gis>
				<main />
			</LogServer>
			<Portal>
				<db>
					<file path="Portal/WEB-INF/classes/proxool.xml">
						<key template="jdbc:oracle:thin:@[db_ip]:[db_port]:[db_sid]">/something-else-entirely/proxool/driver-url</key>
						<key template="[portal_user]" attribute="value">/something-else-entirely/proxool/driver-properties/property[@name='user']</key>
						<key template="[portal_pwd]" attribute="value">/something-else-entirely/proxool/driver-properties/property[@name='password']</key>					
					</file>				
					<!--file path="Portal/OneMapBuilder/proxool.xml">
						<key template="jdbc:oracle:thin:@[db_ip]:[db_port]:[db_sid]">/something-else-entirely/proxool/driver-url</key>
						<key template="[manager_user]" attribute="value">/something-else-entirely/proxool/driver-properties/property[@name='user']</key>
						<key template="[manager_pwd]" attribute="value">/something-else-entirely/proxool/driver-properties/property[@name='password']</key>										
					</file-->
				</db>
				<gis>
					<file path="Portal/WEB-INF/classes/service.properties">
						<key template="http://[gis_ip]:[gis_port]/RemoteRest/services/usa/MapServer">baseMapService</key></file>			
					<file path="Portal/WEB-INF/classes/systemconfig.properties">
						<key template="http://[sysrest_ip]:[sysrest_port]/SysRestServices">path</key>				
					</file>
				</gis>
				<main>
					<file path="Portal/WEB-INF/classes/UploadConfig.properties">
						<key template="[OneMapHome]\temp\ServiceUploadTemp">temppath</key>
						<key template="[OneMapHome]\temp\ServiceUploaded\">path</key>
						<key template="[main_upload_num]">maxfilesize</key></file>
					<file path="Portal/WEB-INF/classes/systemconfig.properties">
						<key template="http://[main_ip]:[main_port]/GeoShareManager">snappath</key>
						<!--key template="http://[main_ip]:[main_port]/GeoShareManager/SnapManage">snapservlet</key-->
						<key template="http://[geoportal_ip]:[geoportal_port]/GeoPortal/catalog/search/search.page">meta_catalog</key>
						<key template="http://[geoportal_ip]:[geoportal_port]/GeoPortal/servlet/viewmetadata?mapserviceid=">meta_query</key>
						<key template="[TomcatAppPath]\application\">appPath</key>
						<key template="[OneMapHome]\temp\userspace">userspacePath</key>
						<key template="[TomcatAppPath]\Portal\FlexTemplate">ria_flex_templatePath</key>
						<key template="http://[main_ip]:[main_port]/ShareExchange/servlet/LoginServlet">ShareExchangeUrl</key>
					</file>
				</main>
				<token>
					<file path="Portal/WEB-INF/classes/service.properties">
						<key template="http://[token_ip]:[token_port]/RemoteTokenServer">tokenurl</key></file>			
					<file path="Portal/FlexTemplate/TokenServer.xml">
						<key template="http://[token_ip]:[token_port]/RemoteTokenServer">/configuration/url</key>
					</file>
				</token>
				<web>
					<file path="Portal/WEB-INF/classes/systemconfig.properties">
						<key template="[web_user]">userid</key>
						<key template="[web_pwd]">password</key>
						<key template="http://[web_ip]:[web_port]/Portal/preview">portal_snapservlet</key>
						<key template="http://[web_ip]:[web_port]/application/">app_http_path</key>					
						<key template="[web_csw]">meta_geoportal</key>						
					</file>
					<file path="Portal/WEB-INF/classes/downloadcenter.properties">
						<key template="[TomcatAppPath]\Portal\downloadcenterFile/">physical_path</key>
						<key template="http://[web_ip]:[web_port]/Portal/downloadcenterFile/">http_path</key>
					</file>
				</web>
				<msg>
					<file path="Portal/WEB-INF/classes/jms.properties">
						<key template="[msg_ip]">msg_ip</key>
						<key template="[msg_port]">msg_port</key>
					</file>
				</msg>
			</Portal>
			<Remote>
				<db>
					<file path="Remote/WEB-INF/classes/security.xml">
						<key template="[manager_user]">/properties/entry[@key='DB_UserName']</key>
						<key template="[manager_pwd]" encrypt="true">/properties/entry[@key='DB_UserPwd']</key>
						<key template="jdbc:oracle:thin:@[db_ip]:[db_port]:[db_sid]">/properties/entry[@key='DB_URL']</key></file>
					<file path="Remote/WEB-INF/classes/proxool.xml">
						<key template="jdbc:h2:tcp://[db_h2]/mem:geosharemdb;MODE=Oracle;DB_CLOSE_DELAY=-1;DB_CLOSE_ON_EXIT=false">/something-else-entirely/proxool[1]/driver-url</key>
						<key template="jdbc:oracle:thin:@[db_ip]:[db_port]:[db_sid]">/something-else-entirely/proxool[2]/driver-url</key>
						<key template="[manager_user]" attribute="value">/something-else-entirely/proxool[2]/driver-properties/property[@name='user']</key>
						<key template="[manager_pwd]" attribute="value">/something-else-entirely/proxool[2]/driver-properties/property[@name='password']</key>					
					</file>
					<file path="Remote/WEB-INF/web.xml">
						<key template="[OneMapHome]\arcgis\license">/default:web-app/default:servlet[7]/default:init-param/default:param-value</key></file>
				</db>
				<gis>
					<file path="Remote/WEB-INF/classes/resources/rest-config.properties">
						<key template="http://[gis_ip]:[gis_port]/arcgis_js_api/library/arcgis/">jsapi.arcgis</key>
						<key template="http://[gis_ip]:[gis_port]/arcgis_js_api/sdk/help/jsapi_start.htm">jsapi.arcgis.sdk</key>
						<key template="http://[gis_ip]:[gis_port]/arcgis_js_api/library/arcgis/js/dojo/dijit/themes/tundra/tundra.css">jsapi.arcgis.css</key>
						<key template="http://[gis_ip]:8399/arcgis/sdk/rest">base.url</key></file>				
					<file path="Remote/WEB-INF/classes/security.xml">
						<key template="[gis_sharekey]" encrypt="true">/properties/entry[@key='SharedKey']</key></file>
					<file path="Remote/WEB-INF/classes/log4j.properties">
						<key template="[OneMapHome]/temp/ws-server/srvmon_out">log4j.log.dir</key></file>
					<file path="Remote/WEB-INF/classes/services-monitor.xml">
						<key template="[gis_ip]">/services-monitor/localAddr</key>
						<key template="[gis_port]">/services-monitor/localPort</key></file>			
					<file path="Remote/WEB-INF/classes/server.properties">
						<key template="[gis_ip]">com.esri.rest.HOST</key>
						<key template="[gis_ip]">com.esri.rest.DOMAIN</key>
						<key template="[gis_ags_user]">com.esri.USER_NAME</key>
						<key template="[gis_ags_pwd]" encrypt="true">com.esri.rest.PASSWORD</key>
						<key template="http://[gis_ip]:[gis_port]/RemoteServices">com.esri.rest.SOAP_URL</key>
						<key template="https://[gis_ip]:[gis_services_port]/RemoteServices">com.esri.rest.SOAP_HTTPS_URL</key>
						<key template="http://[gis_ip]:[gis_port]/RemoteRest/login">onemap.server.security.login</key>
					</file>
				</gis>
				<token>
					<file path="Remote/WEB-INF/classes/security.xml">
						<key template="http://[token_ip]:[token_port]/RemoteTokenServer">/properties/entry[@key='TokenServiceURL']</key></file>			
				</token>
			</Remote>
			<RemoteRest>
				<db>
					<file path="RemoteRest/WEB-INF/classes/security.xml">
						<key template="[manager_user]">/properties/entry[@key='DB_UserName']</key>
						<key template="[manager_pwd]" encrypt="true">/properties/entry[@key='DB_UserPwd']</key>
						<key template="jdbc:oracle:thin:@[db_ip]:[db_port]:[db_sid]">/properties/entry[@key='DB_URL']</key></file>
					<file path="RemoteRest/WEB-INF/classes/proxool.xml">
						<key template="jdbc:h2:tcp://[db_h2]/mem:geosharemdb;MODE=Oracle;DB_CLOSE_DELAY=-1;DB_CLOSE_ON_EXIT=false">/something-else-entirely/proxool[1]/driver-url</key>
						<key template="jdbc:oracle:thin:@[db_ip]:[db_port]:[db_sid]">/something-else-entirely/proxool[2]/driver-url</key>
						<key template="[manager_user]" attribute="value">/something-else-entirely/proxool[2]/driver-properties/property[@name='user']</key>
						<key template="[manager_pwd]" attribute="value">/something-else-entirely/proxool[2]/driver-properties/property[@name='password']</key>					
					</file>			
					<file path="RemoteRest/WEB-INF/web.xml">
						<key template="[OneMapHome]\arcgis\license">/default:web-app/default:servlet[24]/default:init-param/default:param-value</key></file>
				</db>
				<gis>
					<file path="RemoteRest/WEB-INF/classes/resources/rest-config.properties">
						<key template="http://[gis_ip]:[gis_port]/arcgis_js_api/library/arcgis/">jsapi.arcgis</key>
						<key template="http://[gis_ip]:[gis_port]/arcgis_js_api/sdk/help/jsapi_start.htm">jsapi.arcgis.sdk</key>
						<key template="http://[gis_ip]:[gis_port]/arcgis_js_api/library/arcgis/js/dojo/dijit/themes/tundra/tundra.css">jsapi.arcgis.css</key>
						<key template="http://[gis_ip]:8399/arcgis/sdk/rest">base.url</key></file>
					<file path="RemoteRest/WEB-INF/classes/server.properties">
						<key template="[gis_ags_ip]">com.esri.rest.HOST</key>
						<key template="[gis_ags_ip]">com.esri.rest.DOMAIN</key>
						<key template="[gis_ags_user]">com.esri.USER_NAME</key>
						<key template="[gis_ags_pwd]" encrypt="true">com.esri.rest.PASSWORD</key>
						<key template="http://[gis_ip]:[gis_port]/RemoteServices">com.esri.rest.SOAP_URL</key>
						<key template="https://[gis_ip]:[gis_services_port]/RemoteServices">com.esri.rest.SOAP_HTTPS_URL</key>
						<key template="http://[gis_ip]:[gis_port]/RemoteRest/login">onemap.server.security.login</key>
					</file>
					<file path="RemoteRest/WEB-INF/classes/security.xml">
						<key template="[gis_sharekey]" encrypt="true">/properties/entry[@key='SharedKey']</key></file>
					<file path="RemoteRest/WEB-INF/classes/services-monitor.xml">
						<key template="[gis_ip]">/services-monitor/localAddr</key>
						<key template="[gis_port]">/services-monitor/localPort</key></file>
					<file path="RemoteRest/WEB-INF/classes/log4j.properties">
						<key template="[OneMapHome]/temp/ws-server/srvmon">log4j.log.dir</key>
					</file>					
					<file path="RemoteRest/WEB-INF/classes/featureservice.properties">
						<key template="http://[gis_ip]:[gis_port]/arcgis/rest/services/regioncontrol/MapServer/export?bboxSR\=&amp;layers\=0&amp;imageSR\=&amp;format\=png&amp;transparent\=false&amp;dpi\=96&amp;time\=&amp;layerTimeOptions\=&amp;f\=image&amp;bbox\= featureservice=">mapservice</key>
						<key template="http://[gis_ip]:[gis_port]/arcgis/rest/services/regioncontrol/FeatureServer/0/query?objectIds\=&amp;time\=&amp;geometry\=&amp;geometryType\=esriGeometryEnvelope&amp;inSR\=&amp;spatialRel\=esriSpatialRelIntersects&amp;relationParam\=&amp;outFields\=&amp;returnGeometry\=true&amp;returnCountOnly\=false&amp;returnIdsOnly\=false&amp;f\=json&amp;where\=REGIONID%3D">featureservice</key>
					</file>
				</gis>
				<token>
					<file path="RemoteRest/WEB-INF/classes/security.xml">
						<key template="http://[token_ip]:[token_port]/RemoteTokenServer">/properties/entry[@key='TokenServiceURL']</key></file>				
				</token>
			</RemoteRest>
			<RemoteServices>
				<db>
					<file path="RemoteServices/WEB-INF/classes/security.xml">
						<key template="[manager_user]">/properties/entry[@key='DB_UserName']</key>
						<key template="[manager_pwd]" encrypt="true">/properties/entry[@key='DB_UserPwd']</key>
						<key template="jdbc:oracle:thin:@[db_ip]:[db_port]:[db_sid]">/properties/entry[@key='DB_URL']</key></file>	
					<file path="RemoteServices/WEB-INF/classes/proxool.xml">
						<key template="jdbc:h2:tcp://[db_h2]/mem:geosharemdb;MODE=Oracle;DB_CLOSE_DELAY=-1;DB_CLOSE_ON_EXIT=false">/something-else-entirely/proxool[1]/driver-url</key>
						<key template="jdbc:oracle:thin:@[db_ip]:[db_port]:[db_sid]">/something-else-entirely/proxool[2]/driver-url</key>
						<key template="[manager_user]" attribute="value">/something-else-entirely/proxool[2]/driver-properties/property[@name='user']</key>
						<key template="[manager_pwd]" attribute="value">/something-else-entirely/proxool[2]/driver-properties/property[@name='password']</key>						
					</file>					
				</db>
				<gis>
					<file path="RemoteServices/WEB-INF/classes/resources/rest-config.properties">
						<key template="http://[gis_ip]:[gis_port]/arcgis_js_api/library/arcgis/">jsapi.arcgis</key>
						<key template="http://[gis_ip]:[gis_port]/arcgis_js_api/sdk/help/jsapi_start.htm">jsapi.arcgis.sdk</key>
						<key template="http://[gis_ip]:[gis_port]/arcgis_js_api/library/arcgis/js/dojo/dijit/themes/tundra/tundra.css">jsapi.arcgis.css</key>
						<key template="http://[gis_ip]:8399/arcgis/sdk/rest">base.url</key></file>				
					<file path="RemoteServices/WEB-INF/classes/arcgis_wshandler.properties">
						<key template="[gis_ags_ip]">arcgis.som.domain</key>
						<key template="[gis_ags_ip]">arcgis.som.resource.hosts</key>
						<key template="[gis_ags_user]">arcgis.som.username</key>
						<key template="[gis_ags_pwd]" encrypt="true">arcgis.som.password</key></file>	
					<file path="RemoteServices/WEB-INF/classes/security.xml">
						<key template="[gis_sharekey]" encrypt="true">/properties/entry[@key='SharedKey']</key></file>
					<file path="RemoteServices/WEB-INF/classes/server.properties">
						<key template="[gis_ags_ip]">com.esri.rest.HOST</key>
						<key template="[gis_ags_ip]">com.esri.rest.DOMAIN</key>
						<key template="[gis_ags_user]">com.esri.USER_NAME</key>
						<key template="[gis_ags_pwd]" encrypt="true">com.esri.rest.PASSWORD</key>
						<key template="http://[gis_ip]:[gis_port]/RemoteServices">com.esri.rest.SOAP_URL</key>
						<key template="https://[gis_ip]:[gis_services_port]/RemoteServices">com.esri.rest.SOAP_HTTPS_URL</key>
						<key template="http://[gis_ip]:[gis_port]/RemoteRest/login">onemap.server.security.login</key>
					</file>					
					<file path="RemoteServices/WEB-INF/classes/services-monitor.xml">
						<key template="[gis_ip]">/services-monitor/localAddr</key>
						<key template="[gis_port]">/services-monitor/localPort</key></file>
					<file path="RemoteServices/WEB-INF/classes/log4j.properties">
						<key template="[OneMapHome]/temp/ws-server/srvmon_soap">log4j.log.dir</key></file>				
				</gis>
				<token>
					<file path="RemoteServices/WEB-INF/classes/security.xml">
						<key template="http://[token_ip]:[token_port]/RemoteTokenServer">/properties/entry[@key='TokenServiceURL']</key></file>				
				</token>
			</RemoteServices>
			<RemoteTokenServer>
				<db>
					<file path="RemoteTokenServer/WEB-INF/classes/security.xml">
						<key template="[manager_user]">/properties/entry[@key='DB_UserName']</key>
						<key template="[manager_pwd]" encrypt="true">/properties/entry[@key='DB_UserPwd']</key>
						<key template="jdbc:oracle:thin:@[db_ip]:[db_port]:[db_sid]">/properties/entry[@key='DB_URL']</key></file>						
				</db>
				<gis>
					<file path="RemoteTokenServer/WEB-INF/classes/security.xml">
						<key template="[gis_sharekey]" encrypt="true">/properties/entry[@key='SharedKey']</key></file>				
				</gis>
				<token>
					<file path="RemoteTokenServer/WEB-INF/classes/security.xml">
						<key template="http://[token_ip]:[token_port]/RemoteTokenServer">/properties/entry[@key='TokenServiceURL']</key></file>				
				</token>
			</RemoteTokenServer>
			<!--RIA_APP_WIZARD>
				<main>
					<file path="RIA_APP_WIZARD/WEB-INF/classes/manager_config.properties">
						<key template="[main_ip]:[main_port]">manager_host</key></file>			
				</main>
				<token>
					<file path="RIA_APP_WIZARD/TokenServerConfig.xml">
						<key template="http://[token_ip]:[token_port]">/configuration/url</key></file>
					<file path="RIA_APP_WIZARD/templates/FlexTemplate/Deploy/TokenServer.xml">
						<key template="http://[token_ip]:[token_port]/RemoteTokenServer">/configuration/url</key></file>
					<file path="RIA_APP_WIZARD/templates/SLTemplate/Deploy/SilverlightViewerDemo/TokenServer.xml">
						<key template="http://[token_ip]:[token_port]/RemoteTokenServer">/configuration/url</key></file>			
				</token>
				<web>
					<file path="RIA_APP_WIZARD/WEB-INF/classes/manager_config.properties">
						<key template="[flex_ip]:[flex_port]">fl_hostname</key>
						<key template="[sl_ip]:[sl_port]">sl_hostname</key>
						<key template="[iis_root]">iis_root</key></file>	
					<file path="RIA_APP_WIZARD/TemplatePathConfig.xml">
						<key template="http://[ria_ip]:[ria_port]/RIA_APP_WIZARD/templated/">/configuration/srcurl</key></file>			
				</web>
			</RIA_APP_WIZARD-->
			<WMTS>
				<gis>
					<file path="WMTS/WEB-INF/conf/log4j.properties">
						<key template="[OneMapHome]/Tomcat6.0.29/webapps/WMTS/WEB-INF/logs">log4j.log.dir</key></file>	
					<file path="WMTS/WEB-INF/conf/config.properties">
						<key template="http://[wmts_ip]:[wmts_portt]">ARCGISSERVER_REST_URI_PORT</key>
						<key template="http://[wmts_ip]:[wmts_port]">WMTS_URI_PORT</key></file>
				</gis>
			</WMTS>
			<TileServices>
				<db>
					<file path="TileServices/WEB-INF/classes/security.xml">
						<key template="[manager_user]">/properties/entry[@key='DB_UserName']</key>
						<key template="[manager_pwd]" encrypt="true">/properties/entry[@key='DB_UserPwd']</key>
						<key template="jdbc:oracle:thin:@[db_ip]:[db_port]:[db_sid]">/properties/entry[@key='DB_URL']</key></file>
					<file path="TileServices/WEB-INF/classes/proxool.xml">
						<key template="jdbc:h2:tcp://[db_h2]/mem:geosharemdb;MODE=Oracle;DB_CLOSE_DELAY=-1;DB_CLOSE_ON_EXIT=false">/something-else-entirely/proxool[1]/driver-url</key>
						<key template="jdbc:oracle:thin:@[db_ip]:[db_port]:[db_sid]">/something-else-entirely/proxool[2]/driver-url</key>
						<key template="[manager_user]" attribute="value">/something-else-entirely/proxool[2]/driver-properties/property[@name='user']</key>
						<key template="[manager_pwd]" attribute="value">/something-else-entirely/proxool[2]/driver-properties/property[@name='password']</key>						
					</file>
				</db>
				<token>
					<file path="TileServices/WEB-INF/classes/security.xml">
						<key template="http://[token_ip]:[token_port]/RemoteTokenServer">/properties/entry[@key='TokenServiceURL']</key></file>			
				</token>
				<gis>
					<file path="TileServices/WEB-INF/classes/security.xml">
						<key template="[gis_sharekey]" encrypt="true">/properties/entry[@key='SharedKey']</key></file>
					<file path="TileServices/WEB-INF/classes/log4j.properties">
						<key template="[OneMapHome]/temp/ws-server/TileServices">log4j.log.dir</key></file>
					<file path="TileServices/WEB-INF/classes/server.properties">
						<!--key template="[gis_ags_ip]">com.esri.rest.HOST</key>
						<key template="[gis_ags_ip]">com.esri.rest.DOMAIN</key-->
						<key template="[gis_ags_user]">com.esri.USER_NAME</key>
						<key template="[gis_ags_pwd]" encrypt="true">com.esri.rest.PASSWORD</key>
						<key template="http://[gis_ip]:[gis_port]/RemoteServices">com.esri.rest.SOAP_URL</key>
						<key template="https://[gis_ip]:[gis_services_port]/RemoteServices">com.esri.rest.SOAP_HTTPS_URL</key>
						<key template="http://[gis_ip]:[gis_port]/RemoteRest/login">onemap.server.security.login</key>
					</file>
					<file path="TileServices/WEB-INF/classes/resources/rest-config.properties">
						<key template="http://[gis_ip]:[gis_port]/arcgis_js_api/library/arcgis/">jsapi.arcgis</key>
						<key template="http://[gis_ip]:[gis_port]/arcgis_js_api/sdk/help/jsapi_start.htm">jsapi.arcgis.sdk</key>
						<key template="http://[gis_ip]:[gis_port]/arcgis_js_api/library/arcgis/js/dojo/dijit/themes/tundra/tundra.css">jsapi.arcgis.css</key>
						<key template="http://[gis_ip]:8399/arcgis/sdk/rest">base.url</key></file>
				</gis>
				<main>
					<file path="TileServices/WEB-INF/classes/conf/system.properties">
						<key template="[TomcatAppPath]\GeoShareManager\download\commonfile">physical_path_commonfile</key>
						<key template="[TomcatAppPath]\GeoShareManager\download\tilemapfile">physical_path_tilemapfile</key>
						<key template="[TomcatAppPath]\GeoShareManager\download\bundlemapfile">physical_path_bundlemapfile</key></file>
					<file path="TileServices/WEB-INF/classes/services-monitor.xml">
						<key template="[tile_ip]">/services-monitor/localAddr</key>
						<key template="[tile_port]">/services-monitor/localPort</key></file>
					<file path="TileServices/WEB-INF/classes/server.properties">
						<key template="[tile_ip]">com.esri.rest.HOST</key>
						<key template="[tile_ip]">com.esri.rest.DOMAIN</key></file>
				</main>
			</TileServices>
			<FileServices>
				<db>
					<file path="FileServices/WEB-INF/classes/security.xml">
						<key template="[manager_user]">/properties/entry[@key='DB_UserName']</key>
						<key template="[manager_pwd]" encrypt="true">/properties/entry[@key='DB_UserPwd']</key>
						<key template="jdbc:oracle:thin:@[db_ip]:[db_port]:[db_sid]">/properties/entry[@key='DB_URL']</key></file>
					<file path="FileServices/WEB-INF/classes/proxool.xml">
						<key template="jdbc:h2:tcp://[db_h2]/mem:geosharemdb;MODE=Oracle;DB_CLOSE_DELAY=-1;DB_CLOSE_ON_EXIT=false">/something-else-entirely/proxool[1]/driver-url</key>
						<key template="jdbc:oracle:thin:@[db_ip]:[db_port]:[db_sid]">/something-else-entirely/proxool[2]/driver-url</key>
						<key template="[manager_user]" attribute="value">/something-else-entirely/proxool[2]/driver-properties/property[@name='user']</key>
						<key template="[manager_pwd]" attribute="value">/something-else-entirely/proxool[2]/driver-properties/property[@name='password']</key>
					</file>
				</db>
				<main>
					<file path="FileServices/WEB-INF/classes/services-monitor.xml">
						<key template="[file_ip]">/services-monitor/localAddr</key>
						<key template="[file_port]">/services-monitor/localPort</key></file>
					<file path="FileServices/WEB-INF/classes/server.properties">
						<key template="[file_ip]">com.esri.rest.HOST</key>
						<key template="[file_ip]">com.esri.rest.DOMAIN</key></file>
				</main>
				<token>
					<file path="FileServices/WEB-INF/classes/security.xml">
						<key template="http://[token_ip]:[token_port]/RemoteTokenServer">/properties/entry[@key='TokenServiceURL']</key></file>			
				</token>
				<gis>
					<file path="FileServices/WEB-INF/classes/security.xml">
						<key template="[gis_sharekey]" encrypt="true">/properties/entry[@key='SharedKey']</key></file>
					<file path="FileServices/WEB-INF/classes/log4j.properties">
						<key template="[OneMapHome]/temp/ws-server/FileServices">log4j.log.dir</key></file>
					<file path="FileServices/WEB-INF/classes/server.properties">
						<!--key template="[gis_ags_ip]">com.esri.rest.HOST</key>
						<key template="[gis_ags_ip]">com.esri.rest.DOMAIN</key-->
						<key template="[gis_ags_user]">com.esri.USER_NAME</key>
						<key template="[gis_ags_pwd]" encrypt="true">com.esri.rest.PASSWORD</key>
						<key template="http://[gis_ip]:[gis_port]/RemoteServices">com.esri.rest.SOAP_URL</key>
						<key template="https://[gis_ip]:[gis_services_port]/RemoteServices">com.esri.rest.SOAP_HTTPS_URL</key>
						<key template="http://[gis_ip]:[gis_port]/RemoteRest/login">onemap.server.security.login</key>
					</file>
					<file path="FileServices/WEB-INF/classes/resources/rest-config.properties">
						<key template="http://[gis_ip]:[gis_port]/arcgis_js_api/library/arcgis/">jsapi.arcgis</key>
						<key template="http://[gis_ip]:[gis_port]/arcgis_js_api/sdk/help/jsapi_start.htm">jsapi.arcgis.sdk</key>
						<key template="http://[gis_ip]:[gis_port]/arcgis_js_api/library/arcgis/js/dojo/dijit/themes/tundra/tundra.css">jsapi.arcgis.css</key>
						<key template="http://[gis_ip]:8399/arcgis/sdk/rest">base.url</key></file>
				</gis>
			</FileServices>
			<ServiceAggregatorServer>
				<db>
					<file path="ServiceAggregatorServer/WEB-INF/classes/security.xml">
						<key template="[manager_user]">/properties/entry[@key='DB_UserName']</key>
						<key template="[manager_pwd]" encrypt="true">/properties/entry[@key='DB_UserPwd']</key>
						<key template="jdbc:oracle:thin:@[db_ip]:[db_port]:[db_sid]">/properties/entry[@key='DB_URL']</key></file>
					<file path="ServiceAggregatorServer/WEB-INF/classes/proxool.xml">
						<key template="jdbc:h2:tcp://[db_h2]/mem:geosharemdb;MODE=Oracle;DB_CLOSE_DELAY=-1;DB_CLOSE_ON_EXIT=false">/something-else-entirely/proxool[1]/driver-url</key>
						<key template="jdbc:oracle:thin:@[db_ip]:[db_port]:[db_sid]">/something-else-entirely/proxool[2]/driver-url</key>
						<key template="[manager_user]" attribute="value">/something-else-entirely/proxool[2]/driver-properties/property[@name='user']</key>
						<key template="[manager_pwd]" attribute="value">/something-else-entirely/proxool[2]/driver-properties/property[@name='password']</key>
					</file>
				</db>
				<token>
					<file path="ServiceAggregatorServer/WEB-INF/classes/security.xml">
						<key template="http://[token_ip]:[token_port]/RemoteTokenServer">/properties/entry[@key='TokenServiceURL']</key></file>			
				</token>
				<gis>
					<file path="ServiceAggregatorServer/WEB-INF/classes/security.xml">
						<key template="[gis_sharekey]" encrypt="true">/properties/entry[@key='SharedKey']</key></file>
					<file path="ServiceAggregatorServer/WEB-INF/classes/log4j.properties">
						<key template="[OneMapHome]/temp/ws-server/ServiceAggregatorServer">log4j.log.dir</key></file>
					<file path="ServiceAggregatorServer/WEB-INF/classes/resources/rest-config.properties">
						<key template="http://[gis_ip]:[gis_port]/arcgis_js_api/library/arcgis/">jsapi.arcgis</key>
						<key template="http://[gis_ip]:[gis_port]/arcgis_js_api/sdk/help/jsapi_start.htm">jsapi.arcgis.sdk</key>
						<key template="http://[gis_ip]:[gis_port]/arcgis_js_api/library/arcgis/js/dojo/dijit/themes/tundra/tundra.css">jsapi.arcgis.css</key>
						<key template="http://[gis_ip]:8399/arcgis/sdk/rest">base.url</key></file>
					<file path="ServiceAggregatorServer/WEB-INF/classes/server.properties">
						<key template="[gis_ags_ip]">com.esri.rest.HOST</key>
						<key template="[gis_ags_ip]">com.esri.rest.DOMAIN</key>
						<key template="[gis_ags_user]">com.esri.USER_NAME</key>
						<key template="[gis_ags_pwd]" encrypt="true">com.esri.rest.PASSWORD</key>
						<key template="http://[gis_ip]:[gis_port]/RemoteServices">com.esri.rest.SOAP_URL</key>
						<key template="https://[gis_ip]:[gis_services_port]/RemoteServices">com.esri.rest.SOAP_HTTPS_URL</key>
						<key template="http://[gis_ip]:[gis_port]/RemoteRest/login">onemap.server.security.login</key>
					</file>						
				</gis>
				<main>
					<file path="ServiceAggregatorServer/WEB-INF/classes/serviceaggregators_zh_CN.properties">
						<key template="[TomcatAppPath]\ServiceAggregatorServer\WEB-INF\classes\service-aggregators.xml">service-aggregator-path</key>
						<key template="[TomcatAppPath]\ServiceAggregatorServer\WEB-INF\classes\cache-conf.xml">cache-conf-path</key>
					</file>
					<file path="ServiceAggregatorServer/WEB-INF/classes/services-monitor.xml">
						<key template="[aggregator_ip]">/services-monitor/localAddr</key>
						<key template="[aggregator_port]">/services-monitor/localPort</key></file>
				</main>
			</ServiceAggregatorServer>
			<ShareExchange>
				<db>
					<file path="ShareExchange/WEB-INF/classes/conf/hibernate.cfg.xml">
						<key template="jdbc:oracle:thin:@[db_ip]:[db_port]:[db_sid]">/hibernate-configuration/session-factory/property[@name='connection.url']</key>
						<key template="[manager_user]">/hibernate-configuration/session-factory/property[@name='connection.username']</key>
						<key template="[manager_pwd]">/hibernate-configuration/session-factory/property[@name='connection.password']</key>
					</file>
					<file path="ShareExchange/WEB-INF/web.xml">
						<key template="[OneMapHome]\arcgis\license">/default:web-app/default:servlet[24]/default:init-param/default:param-value</key></file>				
				</db>
				<main>
					<file path="ShareExchange/WEB-INF/classes/LocalServiceFileConfig.properties">
						<key template="[OneMapHome]/temp/ServiceUploadTemp">temppath</key>
						<key template="[OneMapHome]/temp/ServiceUploaded/">path</key>
					</file>
					<file path="ShareExchange/WEB-INF/classes/LocalServiceFileConfig.properties">
						<key template="[main_upload_level]">level</key>
						<key template="[main_upload_num]">maxfilesize</key>
					</file>
					<file path="ShareExchange/WEB-INF/classes/log4j.properties">
						<key template="[OneMapHome]/temp/shareexchange.log">log4j.appender.logfile.File</key>
					</file>
					<file path="ShareExchange/WEB-INF/classes/resinfoconfig.properties">
						<key template="[OneMapHome]/temp/ServiceUploaded/">uploadpath</key>
					</file>
				</main>
			</ShareExchange>
			<SysRestServices>
				<db>
					<file path="SysRestServices/WEB-INF/classes/conf/hibernate.cfg.xml">
						<key template="jdbc:oracle:thin:@[db_ip]:[db_port]:[db_sid]">/hibernate-configuration/session-factory/property[@name='connection.url']</key>
						<key template="[manager_user]">/hibernate-configuration/session-factory/property[@name='connection.username']</key>
						<key template="[manager_pwd]">/hibernate-configuration/session-factory/property[@name='connection.password']</key>
					</file>
					<file path="SysRestServices/WEB-INF/classes/log4j.properties">
						<key template="[OneMapHome]/temp/SysRestServices.log">log4j.appender.logfile.File</key>
					</file>
				</db>
			</SysRestServices>
		</tomcat>
		<services path="services">
			<activemq5.4.1>
				<msg />
			</activemq5.4.1>
			<GeoShareMonitorAgent>
				<agent>
					<file path="GeoShareMonitorAgent/config.properties">
						<key template="[agent_ip]">ip</key>
						<key template="[agent_port]">port</key></file>			
				</agent>
			</GeoShareMonitorAgent>
			<H2CommonMemDB>
				<db>
					<file path="H2CommonMemDB/memdb-config.properties">
						<key template="jdbc:h2:tcp://[db_h2]/mem:geosharemdb;MODE=Oracle;DB_CLOSE_DELAY=-1;DB_CLOSE_ON_EXIT=false">memdb.url</key>
					</file>			
				</db>
			</H2CommonMemDB>
		</services>
	</FileMapping>
</root>
